[
  {
    "id": "prod-001",
    "name": "MacBook Pro 16\" M3 Max",
    "description": "Apple M3 Max chip with 14-core CPU, 30-core GPU, 36GB unified memory",
    "category": "Electronics",
    "subcategory": "Laptops",
    "price": 3499.99,
    "currency": "USD",
    "stock": 45,
    "sku": "MBP16-M3MAX-36",
    "brand": "Apple",
    "tags": ["laptop", "apple", "professional", "m3", "high-performance"],
    "specifications": {
      "processor": "Apple M3 Max",
      "cores": 14,
      "gpu": "30-core GPU",
      "ram": "36GB",
      "storage": "1TB SSD",
      "display": "16.2-inch Liquid Retina XDR",
      "resolution": "3456x2234",
      "battery": "22 hours",
      "weight": "2.14 kg",
      "ports": ["Thunderbolt 4 x3", "HDMI", "SDXC", "MagSafe 3", "Headphone jack"]
    },
    "images": [
      { "url": "https://cdn.example.com/products/mbp16-front.jpg", "alt": "MacBook Pro 16 Front", "isPrimary": true },
      { "url": "https://cdn.example.com/products/mbp16-side.jpg", "alt": "MacBook Pro 16 Side", "isPrimary": false }
    ],
    "variants": [
      { "id": "var-001", "name": "Space Black", "sku": "MBP16-M3MAX-36-SB", "priceModifier": 0, "stock": 20 },
      { "id": "var-002", "name": "Silver", "sku": "MBP16-M3MAX-36-SL", "priceModifier": 0, "stock": 25 }
    ],
    "rating": 4.9,
    "reviewCount": 1247,
    "reviews": [
      { "userId": "user-005", "userName": "TechEnthusiast", "rating": 5, "comment": "Best laptop I've ever owned!", "createdAt": "2024-12-01T10:30:00Z" }
    ],
    "shipping": { "weight": 2.5, "freeShipping": true, "estimatedDays": 3 },
    "active": true,
    "featured": true,
    "createdAt": "2024-01-15T10:00:00Z",
    "updatedAt": "2025-01-20T16:45:00Z"
  },
  {
    "id": "prod-002",
    "name": "iPhone 15 Pro Max 256GB",
    "description": "A17 Pro chip, Titanium design, 48MP camera system",
    "category": "Electronics",
    "subcategory": "Smartphones",
    "price": 1199.99,
    "currency": "USD",
    "stock": 230,
    "sku": "IP15PM-256-TI",
    "brand": "Apple",
    "tags": ["smartphone", "apple", "iphone", "5g", "titanium"],
    "specifications": {
      "processor": "A17 Pro",
      "ram": "8GB",
      "storage": "256GB",
      "display": "6.7-inch Super Retina XDR",
      "camera": { "main": "48MP", "ultrawide": "12MP", "telephoto": "12MP" },
      "battery": "4422mAh"
    },
    "images": [
      { "url": "https://cdn.example.com/products/ip15pm-front.jpg", "alt": "iPhone 15 Pro Max Front", "isPrimary": true }
    ],
    "variants": [
      { "id": "var-003", "name": "Natural Titanium", "sku": "IP15PM-256-NT", "priceModifier": 0, "stock": 80 },
      { "id": "var-004", "name": "Blue Titanium", "sku": "IP15PM-256-BT", "priceModifier": 0, "stock": 60 }
    ],
    "rating": 4.8,
    "reviewCount": 3456,
    "reviews": [],
    "shipping": { "weight": 0.221, "freeShipping": true, "estimatedDays": 2 },
    "active": true,
    "featured": true,
    "createdAt": "2024-02-01T08:00:00Z",
    "updatedAt": "2025-01-18T11:30:00Z"
  },
  {
    "id": "prod-003",
    "name": "Sony WH-1000XM5 Wireless Headphones",
    "description": "Industry-leading noise cancellation with 30-hour battery life",
    "category": "Electronics",
    "subcategory": "Audio",
    "price": 349.99,
    "currency": "USD",
    "stock": 156,
    "sku": "SONY-WH1000XM5",
    "brand": "Sony",
    "tags": ["headphones", "wireless", "noise-cancelling", "sony", "audio"],
    "specifications": {
      "driver": "30mm",
      "bluetooth": "5.2",
      "batteryLife": "30 hours",
      "noiseCancellation": "Adaptive",
      "codec": ["LDAC", "AAC", "SBC"]
    },
    "images": [
      { "url": "https://cdn.example.com/products/xm5-black.jpg", "alt": "WH-1000XM5 Black", "isPrimary": true }
    ],
    "variants": [
      { "id": "var-007", "name": "Black", "sku": "SONY-XM5-BLK", "priceModifier": 0, "stock": 100 },
      { "id": "var-008", "name": "Silver", "sku": "SONY-XM5-SLV", "priceModifier": 0, "stock": 56 }
    ],
    "rating": 4.7,
    "reviewCount": 2890,
    "reviews": [],
    "shipping": { "weight": 0.5, "freeShipping": true, "estimatedDays": 3 },
    "active": true,
    "featured": false,
    "createdAt": "2024-03-10T12:00:00Z",
    "updatedAt": "2025-01-15T09:20:00Z"
  },
  {
    "id": "prod-004",
    "name": "Samsung 65\" Neo QLED 8K Smart TV",
    "description": "Quantum Matrix Technology Pro with Neural Quantum Processor 8K",
    "category": "Electronics",
    "subcategory": "TVs",
    "price": 2999.99,
    "currency": "USD",
    "stock": 28,
    "sku": "SAMS-QN65QN900C",
    "brand": "Samsung",
    "tags": ["tv", "8k", "smart-tv", "samsung", "qled"],
    "specifications": {
      "screenSize": "65 inches",
      "resolution": "7680x4320 (8K)",
      "panelType": "Neo QLED",
      "hdr": ["HDR10+", "Dolby Vision", "HLG"],
      "refreshRate": "120Hz",
      "ports": { "hdmi": 4, "usb": 3 }
    },
    "images": [
      { "url": "https://cdn.example.com/products/qn900c-front.jpg", "alt": "Samsung 8K TV Front", "isPrimary": true }
    ],
    "variants": [],
    "rating": 4.6,
    "reviewCount": 567,
    "reviews": [],
    "shipping": { "weight": 28.5, "freeShipping": false, "shippingCost": 99.99, "estimatedDays": 7 },
    "active": true,
    "featured": true,
    "createdAt": "2024-04-20T14:30:00Z",
    "updatedAt": "2025-01-10T17:00:00Z"
  },
  {
    "id": "prod-005",
    "name": "Logitech MX Master 3S Wireless Mouse",
    "description": "Advanced wireless mouse with MagSpeed scrolling and 8K DPI",
    "category": "Accessories",
    "subcategory": "Input Devices",
    "price": 99.99,
    "currency": "USD",
    "stock": 342,
    "sku": "LOGI-MXM3S",
    "brand": "Logitech",
    "tags": ["mouse", "wireless", "ergonomic", "logitech", "productivity"],
    "specifications": {
      "sensor": "Darkfield 8000 DPI",
      "buttons": 7,
      "battery": "70 days",
      "connectivity": ["Bluetooth", "Logi Bolt USB"]
    },
    "images": [
      { "url": "https://cdn.example.com/products/mxmaster3s.jpg", "alt": "MX Master 3S", "isPrimary": true }
    ],
    "variants": [
      { "id": "var-009", "name": "Graphite", "sku": "LOGI-MXM3S-GR", "priceModifier": 0, "stock": 200 },
      { "id": "var-010", "name": "Pale Gray", "sku": "LOGI-MXM3S-PG", "priceModifier": 0, "stock": 142 }
    ],
    "rating": 4.8,
    "reviewCount": 4521,
    "reviews": [],
    "shipping": { "weight": 0.3, "freeShipping": true, "estimatedDays": 2 },
    "active": true,
    "featured": false,
    "createdAt": "2024-05-15T09:00:00Z",
    "updatedAt": "2025-01-19T10:15:00Z"
  },
  {
    "id": "prod-006",
    "name": "ASUS ROG Swift PG32UQX Gaming Monitor",
    "description": "32\" 4K 144Hz Mini LED Gaming Monitor with G-SYNC Ultimate",
    "category": "Electronics",
    "subcategory": "Monitors",
    "price": 2499.99,
    "currency": "USD",
    "stock": 23,
    "sku": "ASUS-PG32UQX",
    "brand": "ASUS",
    "tags": ["monitor", "gaming", "4k", "144hz", "mini-led", "rog"],
    "specifications": {
      "screenSize": "32 inches",
      "resolution": "3840x2160 (4K)",
      "refreshRate": "144Hz",
      "responseTime": "1ms GTG",
      "hdr": "DisplayHDR 1400"
    },
    "images": [
      { "url": "https://cdn.example.com/products/pg32uqx-front.jpg", "alt": "ROG Swift Gaming Monitor", "isPrimary": true }
    ],
    "variants": [],
    "rating": 4.5,
    "reviewCount": 234,
    "reviews": [],
    "shipping": { "weight": 12.5, "freeShipping": false, "shippingCost": 49.99, "estimatedDays": 5 },
    "active": true,
    "featured": false,
    "createdAt": "2024-06-01T11:00:00Z",
    "updatedAt": "2025-01-12T14:30:00Z"
  },
  {
    "id": "prod-007",
    "name": "Dyson V15 Detect Absolute Vacuum",
    "description": "Intelligent cordless vacuum with laser dust detection",
    "category": "Home & Garden",
    "subcategory": "Cleaning",
    "price": 749.99,
    "currency": "USD",
    "stock": 67,
    "sku": "DYSON-V15-ABS",
    "brand": "Dyson",
    "tags": ["vacuum", "cordless", "dyson", "smart-home", "cleaning"],
    "specifications": {
      "motor": "Hyperdymium",
      "suction": "230 AW",
      "runtime": "60 minutes",
      "filtration": "HEPA",
      "attachments": ["Fluffy Optic", "Hair screw", "Crevice tool"]
    },
    "images": [
      { "url": "https://cdn.example.com/products/dyson-v15.jpg", "alt": "Dyson V15 Detect", "isPrimary": true }
    ],
    "variants": [],
    "rating": 4.7,
    "reviewCount": 1876,
    "reviews": [],
    "shipping": { "weight": 6.8, "freeShipping": true, "estimatedDays": 4 },
    "active": true,
    "featured": false,
    "createdAt": "2024-07-10T08:30:00Z",
    "updatedAt": "2025-01-08T12:00:00Z"
  },
  {
    "id": "prod-008",
    "name": "Nintendo Switch OLED Model",
    "description": "7-inch OLED screen gaming console with enhanced audio",
    "category": "Gaming",
    "subcategory": "Consoles",
    "price": 349.99,
    "currency": "USD",
    "stock": 189,
    "sku": "NINT-SWITCH-OLED",
    "brand": "Nintendo",
    "tags": ["gaming", "console", "nintendo", "portable", "oled"],
    "specifications": {
      "screen": "7-inch OLED",
      "resolution": "1280x720 (handheld)",
      "storage": "64GB",
      "battery": "4.5-9 hours"
    },
    "images": [
      { "url": "https://cdn.example.com/products/switch-oled-white.jpg", "alt": "Switch OLED White", "isPrimary": true }
    ],
    "variants": [
      { "id": "var-011", "name": "White", "sku": "NINT-OLED-WHT", "priceModifier": 0, "stock": 100 },
      { "id": "var-012", "name": "Neon", "sku": "NINT-OLED-NEON", "priceModifier": 0, "stock": 89 }
    ],
    "rating": 4.9,
    "reviewCount": 8765,
    "reviews": [],
    "shipping": { "weight": 2.1, "freeShipping": true, "estimatedDays": 3 },
    "active": true,
    "featured": true,
    "createdAt": "2024-08-01T10:00:00Z",
    "updatedAt": "2025-01-21T09:00:00Z"
  },
  {
    "id": "prod-009",
    "name": "Bose QuietComfort Ultra Earbuds",
    "description": "True wireless earbuds with spatial audio and world-class noise cancellation",
    "category": "Electronics",
    "subcategory": "Audio",
    "price": 299.99,
    "currency": "USD",
    "stock": 234,
    "sku": "BOSE-QCUE",
    "brand": "Bose",
    "tags": ["earbuds", "wireless", "noise-cancelling", "bose", "spatial-audio"],
    "specifications": {
      "driver": "9.3mm",
      "battery": "6 hours (24 with case)",
      "bluetooth": "5.3",
      "waterResistance": "IPX4"
    },
    "images": [
      { "url": "https://cdn.example.com/products/qc-ultra-earbuds.jpg", "alt": "QC Ultra Earbuds", "isPrimary": true }
    ],
    "variants": [
      { "id": "var-013", "name": "Black", "sku": "BOSE-QCUE-BLK", "priceModifier": 0, "stock": 150 },
      { "id": "var-014", "name": "White Smoke", "sku": "BOSE-QCUE-WS", "priceModifier": 0, "stock": 84 }
    ],
    "rating": 4.6,
    "reviewCount": 1234,
    "reviews": [],
    "shipping": { "weight": 0.15, "freeShipping": true, "estimatedDays": 2 },
    "active": true,
    "featured": false,
    "createdAt": "2024-09-15T14:00:00Z",
    "updatedAt": "2025-01-17T11:45:00Z"
  },
  {
    "id": "prod-010",
    "name": "Razer BlackWidow V4 Pro Keyboard",
    "description": "Premium mechanical gaming keyboard with Razer Green switches",
    "category": "Accessories",
    "subcategory": "Input Devices",
    "price": 229.99,
    "currency": "USD",
    "stock": 112,
    "sku": "RAZER-BWV4P",
    "brand": "Razer",
    "tags": ["keyboard", "gaming", "mechanical", "rgb", "razer"],
    "specifications": {
      "switches": "Razer Green Mechanical",
      "backlight": "Razer Chroma RGB",
      "layout": "Full-size",
      "connectivity": "USB-C"
    },
    "images": [
      { "url": "https://cdn.example.com/products/bwv4pro.jpg", "alt": "BlackWidow V4 Pro", "isPrimary": true }
    ],
    "variants": [],
    "rating": 4.7,
    "reviewCount": 987,
    "reviews": [],
    "shipping": { "weight": 1.8, "freeShipping": true, "estimatedDays": 3 },
    "active": true,
    "featured": false,
    "createdAt": "2024-10-01T16:00:00Z",
    "updatedAt": "2025-01-14T08:30:00Z"
  },
  {
    "id": "prod-011",
    "name": "DJI Mavic 3 Pro Drone",
    "description": "Professional drone with Hasselblad camera and 43-min flight time",
    "category": "Electronics",
    "subcategory": "Drones",
    "price": 2199.99,
    "currency": "USD",
    "stock": 34,
    "sku": "DJI-M3PRO",
    "brand": "DJI",
    "tags": ["drone", "aerial", "4k", "dji", "professional"],
    "specifications": {
      "camera": { "main": "20MP Hasselblad", "medium": "12MP 70mm", "tele": "12MP 166mm" },
      "video": "5.1K/50fps",
      "flightTime": "43 minutes",
      "range": "15km"
    },
    "images": [
      { "url": "https://cdn.example.com/products/mavic3pro.jpg", "alt": "DJI Mavic 3 Pro", "isPrimary": true }
    ],
    "variants": [],
    "rating": 4.8,
    "reviewCount": 567,
    "reviews": [],
    "shipping": { "weight": 0.958, "freeShipping": true, "estimatedDays": 4 },
    "active": true,
    "featured": true,
    "createdAt": "2024-11-15T12:00:00Z",
    "updatedAt": "2025-01-20T10:00:00Z"
  },
  {
    "id": "prod-012",
    "name": "Dell XPS 15 (2024)",
    "description": "Premium Windows laptop with Intel Core Ultra 9 and OLED display",
    "category": "Electronics",
    "subcategory": "Laptops",
    "price": 2299.99,
    "currency": "USD",
    "stock": 56,
    "sku": "DELL-XPS15-2024",
    "brand": "Dell",
    "tags": ["laptop", "dell", "windows", "oled", "ultrabook"],
    "specifications": {
      "processor": "Intel Core Ultra 9 185H",
      "ram": "32GB DDR5",
      "storage": "1TB NVMe SSD",
      "display": "15.6-inch OLED 3.5K",
      "gpu": "NVIDIA RTX 4070"
    },
    "images": [
      { "url": "https://cdn.example.com/products/xps15-2024.jpg", "alt": "Dell XPS 15", "isPrimary": true }
    ],
    "variants": [],
    "rating": 4.5,
    "reviewCount": 345,
    "reviews": [],
    "shipping": { "weight": 1.86, "freeShipping": true, "estimatedDays": 3 },
    "active": true,
    "featured": false,
    "createdAt": "2024-12-01T09:00:00Z",
    "updatedAt": "2025-01-18T14:00:00Z"
  }
]
